pyy/__init__.py
pyy/__main__.py
pyy/main.py
pyy3-1.3.dist-info/METADATA
pyy3-1.3.dist-info/WHEEL
pyy3-1.3.dist-info/entry_points.txt
pyy3-1.3.dist-info/top_level.txt
pyy3-1.3.dist-info/RECORD
