Metadata-Version: 2.4
Name: pyy3
Version: 1.3
Summary: Alternative runner for python for the public+export keywords
Author: Semicolon Studios
Author-email: fossil.org1@gmail.com
Dynamic: author
Dynamic: author-email
Dynamic: summary
